{
  "updated_at": "2026-04-19T22:17:54",
  "pending": [
    {
      "bus_message_id": "52a220eb-98f1-4c7a-82ae-392c57de0406",
      "source_id": "review_52a220eb",
      "subject": "Inbox Review: Post von immocation",
      "created_at": "2026-04-19T10:26:42",
      "original_id": null,
      "original_from": "post@immocation.de",
      "snippet": "Immobilien Newsletter...",
      "proposed_tag": "real-estate",
      "confidence": 30,
      "reason": "Agent real-estate noch nicht aktiv",
      "routing_options": [
        "real-estate",
        "finance",
        "cos",
        "tax"
      ]
    }
  ]
}